rtpPayload_ttml/__init__.py
rtpPayload_ttml/py.typed
rtpPayload_ttml/rtpPayload_ttml.py
rtpPayload_ttml/utfUtils.py
rtpPayload_ttml-0.0.3.dist-info/METADATA
rtpPayload_ttml-0.0.3.dist-info/WHEEL
rtpPayload_ttml-0.0.3.dist-info/top_level.txt
rtpPayload_ttml-0.0.3.dist-info/RECORD
