Metadata-Version: 2.1
Name: rtpPayload-ttml
Version: 0.0.3
Summary: A library for decoding/encoding TTML RTP payloads
Home-page: https://github.com/bbc/rd-apmm-python-lib-rtpPayload_ttml
Author: BBC R&D
Author-email: cloudfit-opensource@rd.bbc.co.uk
License: apache-2.0
Requires-Dist: six
Requires-Dist: flask
Requires-Dist: mypy
